Lecture10/add_shft_mul.v
`timescale 1ns / 1ps

module add_shft_mul (
                     input         clk,
                     input         rst,
                     
                     input signed [7:0]   a, 
                     input signed [15:0]   b,
                     output reg signed [15:0] c,
                     input         start,
                     output        done
                     );

   reg [3:0]                     counter;


   assign done = (counter == 4'd8);

   always@(posedge clk)
     if(rst)
       counter <= 4'd8;
     else if (start)
       counter <= 4'd0;
     else if (counter != 4'd8)
       counter <= counter + 1'b1;
   
    
     always@(posedge clk)
     if(rst)
        c <= 16'd0;
     else if(counter != 4'd7) begin 
        c <= (c>>>1) + (b[counter]? a<<7: 16'd0);
     end
     else if(counter == 4'd7) begin
     c <= c  - (b[counter]? a<<7: 16'd0);
     c <= c>>>1;
     end
endmodule


module add_shft_mul_tb ();

   reg clk, rst;
   reg signed [7:0] a;
   reg signed [15:0] b;
   wire signed [15:0] c;
   reg         start;
   wire        done;
   
   add_shft_mul mult0 (
                       .clk(clk),
                       .rst(rst),
                     
                       .a(a), 
                       .b(b),
                       .c(c),
                       .start(start),
                       .done(done)
                     );   

   initial begin

      $dumpfile("dump.vcd");
      $dumpvars;
      
      rst = 1;
      clk = 1;
      start = 0;

      a= 10;
      b = -2;

      @(posedge clk) #1 rst=0;

      #5 @(posedge clk) #1 start=1;
      @(posedge clk) #1 start=0;

      @(posedge done) $display("%d", c);
      
      @(posedge clk) $finish;
   end
   
   always #10 clk = ~clk;
 
endmodule

Lecture10/dump.vcd
$date
	Thu Oct 24 14:17:59 2019
$end
$version
	Icarus Verilog
$end
$timescale
	1ps
$end
$scope module add_shft_mul_tb $end
$var wire 1 ! done $end
$var wire 16 " c [15:0] $end
$var reg 8 # a [7:0] $end
$var reg 16 $ b [15:0] $end
$var reg 1 % clk $end
$var reg 1 & rst $end
$var reg 1 ' start $end
$scope module mult0 $end
$var wire 8 ( a [7:0] $end
$var wire 16 ) b [15:0] $end
$var wire 1 % clk $end
$var wire 1 & rst $end
$var wire 1 ' start $end
$var wire 1 ! done $end
$var reg 16 * c [15:0] $end
$var reg 4 + counter [3:0] $end
$upscope $end
$upscope $end
$enddefinitions $end
#0
$dumpvars
b1000 +
b0 *
b1111111111111110 )
b1010 (
0'
1&
1%
b1111111111111110 $
b1010 #
b0 "
1!
$end
#10000
0%
#20000
1%
#21000
0&
#30000
0%
#40000
b10100000000 "
b10100000000 *
1%
#41000
1'
#50000
0%
#60000
b11110000000 "
b11110000000 *
0!
b0 +
1%
#61000
0'
#70000
0%
#80000
b1 +
b1111000000 "
b1111000000 *
1%
#90000
0%
#100000
b11011100000 "
b11011100000 *
b10 +
1%
#110000
0%
#120000
b11 +
b100001110000 "
b100001110000 *
1%
#130000
0%
#140000
b100100111000 "
b100100111000 *
b100 +
1%
#150000
0%
#160000
b101 +
b100110011100 "
b100110011100 *
1%
#170000
0%
#180000
b100111001110 "
b100111001110 *
b110 +
1%
#190000
0%
#200000
b111 +
b100111100111 "
b100111100111 *
1%
#210000
0%
#220000
b10011110011 "
b10011110011 *
1!
b1000 +
1%
#230000
0%
#240000
b11101111001 "
b11101111001 *
1%
